README.rst
setup.py
nosetests_json_extended/__init__.py
nosetests_json_extended/plugin.py
nosetests_json_extended/sink.py
nosetests_json_extended/test_plugin.py
nosetests_json_extended/test_sink.py
nosetests_json_extended.egg-info/PKG-INFO
nosetests_json_extended.egg-info/SOURCES.txt
nosetests_json_extended.egg-info/dependency_links.txt
nosetests_json_extended.egg-info/entry_points.txt
nosetests_json_extended.egg-info/not-zip-safe
nosetests_json_extended.egg-info/top_level.txt