Metadata-Version: 1.1
Name: nosetests-json-extended
Version: 0.1.0
Summary: ('Create json logging output for pythonnosetests unittest framework',)
Home-page: http://github.com/thschenk/nosetests-json-extended
Author: Thijs Schenkelaars
Author-email: thijs@schenkelaars.nl
License: UNKNOWN
Platform: UNKNOWN
Classifier: Development Status :: 3 - Alpha
Classifier: Intended Audience :: Developers
Classifier: Operating System :: OS Independent
Classifier: Programming Language :: Python :: 2
Classifier: Programming Language :: Python :: 3
Classifier: Topic :: Software Development :: Testing
